{
    "flip": "(╯°□°）╯︵ ┻━┻",
    "finger": "┌∩┐(◣_◢)┌∩┐",
    "lenny": "( ͡° ͜ʖ ͡°)",
    "song": "¸¸♬·¯·♩¸¸♪·¯·♫¸¸¸♬·¯·♩¸¸♪·¯·♫¸¸",
    "umad": "¯\\_(ツ)_/¯",
    "rifle": "︻デ┳═ー",
    "flipall": "┻━┻︵ \\(°□°)/ ︵ ┻━┻",
    "killer": "(⌐■_■)--︻╦╤─ - - - (╥﹏╥)",
    "bird": "~(‾▼‾)~",
    "fuckyou": "ᶠᶸᶜᵏ♥ᵧₒᵤ",
    "what": "(Ͼ˳Ͽ)..!!!",
    "dance": "♪┏(°.°)┛┗(°.°)┓┗(°.°)┛┏(°.°)┓ ♪",
    "robbery": "Everybody on the floor! This is a robbery (╯°□°)--︻╦╤─ - - -",
    "shooting": "(╯°□°)--︻╦╤─ - - -",
    "sword": "()==[:::::::::::::>",
    "yolo": "Yᵒᵘ Oᶰˡʸ Lᶤᵛᵉ Oᶰᶜᵉ",
    "omg": "◕_◕",
    "celcius": "℃",
    "farenheit": "℉",
    "fish": "¸.·´¯`·.´¯`·.¸¸.·´¯`·.¸><(((º>",
    "peace": "Peace! (‾⌣‾)♉",
    "kirby": "(つ -‘ _ ‘- )つ",
    "perky": "( ๏ Y ๏ )",
    "slenderman": "ϟƖΣNd€RMαN",
    "isee": "☚ (<‿<)☚ I see what you did there.",
    "whatthe": "⨀_⨀",
    "smooth": "(づ ￣ ³￣)づ ⓈⓂⓄⓄⓉⒽ",
    "toss": "(╯°□°）╯︵ ",
    "^": "↑",
    ">": "→",
    "v": "↓",
    "<": "←",
    "zoidberg": "(\\/)(Ö,,,,Ö)(\\/)",
    "<3": "♥"
}